ermini/MANIFEST.in
ermini/README.md
ermini/__init__.py
ermini/celery.py
ermini/requirements.txt
ermini/settings.py
ermini/setup.py
ermini/urls.py
ermini-0.1.2.dist-info/METADATA
ermini-0.1.2.dist-info/WHEEL
ermini-0.1.2.dist-info/top_level.txt
ermini-0.1.2.dist-info/RECORD
