Metadata-Version: 2.1
Name: ermini
Version: 0.1.2
Home-page: https://github.com/crusat/ermini
Author: Aleksey Kuznetsov aka crusat
Author-email: crusat@yandex.ru
License: MIT
Classifier: Development Status :: 4 - Beta
Classifier: Environment :: Web Environment
Classifier: Intended Audience :: Developers
Classifier: License :: OSI Approved :: MIT License
Classifier: Operating System :: OS Independent
Classifier: Programming Language :: Python
Classifier: Framework :: Django
Classifier: Programming Language :: Python :: 3.9
Requires-Dist: asgiref (==3.7.2)
Requires-Dist: async-timeout (==4.0.3)
Requires-Dist: certifi (==2023.7.22)
Requires-Dist: charset-normalizer (==3.3.1)
Requires-Dist: Django (==4.2.6)
Requires-Dist: django-ckeditor (==6.7.0)
Requires-Dist: django-js-asset (==2.1.0)
Requires-Dist: django-solo (==2.1.0)
Requires-Dist: docutils (==0.20.1)
Requires-Dist: environs (==9.5.0)
Requires-Dist: idna (==3.4)
Requires-Dist: importlib-metadata (==6.8.0)
Requires-Dist: jaraco.classes (==3.3.0)
Requires-Dist: keyring (==24.2.0)
Requires-Dist: markdown-it-py (==3.0.0)
Requires-Dist: marshmallow (==3.20.1)
Requires-Dist: mdurl (==0.1.2)
Requires-Dist: more-itertools (==10.1.0)
Requires-Dist: nh3 (==0.2.14)
Requires-Dist: packaging (==23.2)
Requires-Dist: pkginfo (==1.9.6)
Requires-Dist: psycopg2-binary (==2.9.9)
Requires-Dist: Pygments (==2.16.1)
Requires-Dist: python-dotenv (==1.0.0)
Requires-Dist: readme-renderer (==42.0)
Requires-Dist: redis (==5.0.1)
Requires-Dist: requests (==2.31.0)
Requires-Dist: requests-toolbelt (==1.0.0)
Requires-Dist: rfc3986 (==2.0.0)
Requires-Dist: rich (==13.6.0)
Requires-Dist: sqlparse (==0.4.4)
Requires-Dist: twine (==4.0.2)
Requires-Dist: typing-extensions (==4.8.0)
Requires-Dist: urllib3 (==2.0.7)
Requires-Dist: uWSGI (==2.0.22)
Requires-Dist: zipp (==3.17.0)
